MpMatrix/MpMatrix.py
MpMatrix/MpMatrix_tests.py
MpMatrix-1.dist-info/LICENSE
MpMatrix-1.dist-info/METADATA
MpMatrix-1.dist-info/WHEEL
MpMatrix-1.dist-info/entry_points.txt
MpMatrix-1.dist-info/top_level.txt
MpMatrix-1.dist-info/RECORD
