Metadata-Version: 2.1
Name: MpMatrix
Version: 1
Summary: This package contains implementation of the programming library MpMatrix.
Home-page: https://github.com/GlobalCreativeApkDev/INDONESIAN_PROGRAMMERS/tree/main/MpMatrix
Author: GlobalCreativeApkDev
Author-email: globalcreativeapkdev2022@gmail.com
License: MIT
Classifier: Programming Language :: Python :: 3
Classifier: Programming Language :: Python :: 3.7
License-File: LICENSE
